cs/later.py
cs.later-20240630.dist-info/METADATA
cs.later-20240630.dist-info/WHEEL
cs.later-20240630.dist-info/top_level.txt
cs.later-20240630.dist-info/RECORD
