Metadata-Version: 2.1
Name: cs.later
Version: 20240630
Summary: Queue functions for execution later in priority and time order.
Author-email: Cameron Simpson <cs@cskk.id.au>
License: GNU General Public License v3 or later (GPLv3+)
Project-URL: Monorepo Hg/Mercurial Mirror, https://hg.sr.ht/~cameron-simpson/css
Project-URL: Monorepo Git Mirror, https://github.com/cameron-simpson/css
Project-URL: MonoRepo Commits, https://bitbucket.org/cameron_simpson/css/commits/branch/main
Project-URL: Source, https://github.com/cameron-simpson/css/blob/main/lib/python/cs/later.py
Keywords: python3
Classifier: Programming Language :: Python
Classifier: Programming Language :: Python :: 3
Classifier: Development Status :: 4 - Beta
Classifier: Intended Audience :: Developers
Classifier: Operating System :: OS Independent
Classifier: Topic :: Software Development :: Libraries :: Python Modules
Classifier: License :: OSI Approved :: GNU General Public License v3 or later (GPLv3+)
Requires-Dist: cs.context >=20240630
Requires-Dist: cs.deco >=20240630
Requires-Dist: cs.excutils >=20240630
Requires-Dist: cs.logutils >=20240630
Requires-Dist: cs.pfx >=20240630
Requires-Dist: cs.py.func >=20240630
Requires-Dist: cs.queues >=20240412
Requires-Dist: cs.resources >=20240630
Requires-Dist: cs.result >=20240630
Requires-Dist: cs.seq >=20221118
Requires-Dist: cs.threads >=20240630
Requires-Dist: typeguard
